{
  "db_name": "PostgreSQL",
  "query": "\n            UPDATE disputes\n            SET evidence_urls = evidence_urls || $1,\n                admin_notes = COALESCE($2, admin_notes),\n                dispute_status = CASE WHEN dispute_status = 'OPEN' THEN 'UNDER_REVIEW' ELSE dispute_status END,\n                updated_at = now()\n            WHERE id = $3\n            ",
  "describe": {
    "columns": [],
    "parameters": {
      "Left": [
        "TextArray",
        "Text",
        "Uuid"
      ]
    },
    "nullable": []
  },
  "hash": "9b0cf853396b620cc1252befc5099ec61f59c9ad0866353517e030e8050bb9c2"
}
