{
  "db_name": "PostgreSQL",
  "query": "\n            INSERT INTO trust_scores (\n                id, party_id, deals_completed_count, deals_cancelled_count, deals_disputed_count,\n                timeouts_count, no_shows_count, total_completed_value\n            )\n            VALUES ($1, $2, 0, 0, 0, 1, 0, 0)\n            ON CONFLICT (party_id) DO UPDATE SET\n                timeouts_count = trust_scores.timeouts_count + 1,\n                updated_at = now()\n            ",
  "describe": {
    "columns": [],
    "parameters": {
      "Left": [
        "Uuid",
        "Uuid"
      ]
    },
    "nullable": []
  },
  "hash": "d4cd3e5dc0ce90f13c2b5147962d1425c86a86300d4ba9e6129b4a29f352ec64"
}
