{
  "db_name": "PostgreSQL",
  "query": "\n            INSERT INTO user_party_memberships (id, user_id, party_id, member_role, is_active, created_at)\n            VALUES ($1, $2, $3, $4, $5, $6)\n            ON CONFLICT (user_id, party_id) DO UPDATE SET\n                member_role = EXCLUDED.member_role,\n                is_active = true\n            ",
  "describe": {
    "columns": [],
    "parameters": {
      "Left": [
        "Uuid",
        "Uuid",
        "Uuid",
        "Text",
        "Bool",
        "Timestamptz"
      ]
    },
    "nullable": []
  },
  "hash": "ffae2d3e6fc078d5c38930c2b6f5a08aab35da14e72350fd37262de7abebfc86"
}
